fitloop/__init__.py
fitloop/main_class.py
fitloop/main_constants.py
fitloop/defaults/__init__.py
fitloop/defaults/batch_step.py
fitloop/defaults/configure_optimizer.py
fitloop/defaults/epoch_end.py
fitloop/helpers/__init__.py
fitloop/helpers/constants.py
fitloop/helpers/helpers.py
fitloop/helpers/metrics.py
fitloop/helpers/state.py
fitloop/helpers/utils.py
fitloop-0.1.5.dist-info/LICENSE
fitloop-0.1.5.dist-info/METADATA
fitloop-0.1.5.dist-info/WHEEL
fitloop-0.1.5.dist-info/top_level.txt
fitloop-0.1.5.dist-info/RECORD
