Metadata-Version: 2.1
Name: fitloop
Version: 0.1.5
Summary: fitloop trains Pytorch models
Home-page: https://github.com/18alantom/fitloop
Author: Alan
Author-email: 2.alan.tom@gmail.com
License: MIT
Platform: UNKNOWN
Classifier: License :: OSI Approved :: MIT License
Classifier: Programming Language :: Python :: 3.7
Classifier: Topic :: Scientific/Engineering :: Artificial Intelligence
Classifier: Operating System :: OS Independent
Classifier: Framework :: Jupyter
Requires-Dist: torch (~=1.4)
Requires-Dist: matplotlib (~=3.2)
Requires-Dist: numpy (~=1.18)
Requires-Dist: tqdm (~=4.40)
